folio_data_import/BatchPoster.py
folio_data_import/MARCDataImport.py
folio_data_import/UserImport.py
folio_data_import/__init__.py
folio_data_import/__main__.py
folio_data_import/_progress.py
folio_data_import/custom_exceptions.py
folio_data_import/marc_preprocessors/__init__.py
folio_data_import/marc_preprocessors/_preprocessors.py
folio_data_import-0.5.0.dist-info/WHEEL
folio_data_import-0.5.0.dist-info/entry_points.txt
folio_data_import-0.5.0.dist-info/METADATA
folio_data_import-0.5.0.dist-info/RECORD
