Metadata-Version: 2.4
Name: folio_data_import
Version: 0.5.0
Summary: A python module to perform bulk import of data into a FOLIO environment. Currently supports MARC and user data import.
Author: Brooks Travis
Author-email: Brooks Travis <brooks.travis@gmail.com>
License-Expression: MIT
Requires-Dist: folioclient>=1.0.3,<2.0
Requires-Dist: pymarc>=5.2.2
Requires-Dist: pyhumps>=3.8.0
Requires-Dist: tabulate>=0.9.0
Requires-Dist: aiofiles>=24.1.0
Requires-Dist: flake8-black>=0.3.6
Requires-Dist: flake8-bugbear>=24.8.19
Requires-Dist: flake8-bandit>=4.1.1
Requires-Dist: flake8-isort>=6.1.1
Requires-Dist: flake8-docstrings>=1.7.0
Requires-Dist: cyclopts>=4.2.0
Requires-Dist: questionary>=2.1.1
Requires-Dist: folio-uuid>=1.0.0
Requires-Dist: pydantic>=2.12.3
Requires-Dist: redis>=7.1.0 ; extra == 'redis'
Requires-Python: >=3.10, <4.0
Provides-Extra: redis
